processportmonitor/__init__.py
processportmonitor/__main__.py
processportmonitor/monitor.py
processportmonitor-0.1.7.dist-info/LICENSE
processportmonitor-0.1.7.dist-info/METADATA
processportmonitor-0.1.7.dist-info/WHEEL
processportmonitor-0.1.7.dist-info/entry_points.txt
processportmonitor-0.1.7.dist-info/top_level.txt
processportmonitor-0.1.7.dist-info/RECORD
