Metadata-Version: 2.1
Name: processportmonitor
Version: 0.1.7
Summary: Real-time monitoring of active TCP ports used by a specific process (PID)
Home-page: https://github.com/cenab/processportmonitor
Author: Cenab Batu Bora
Author-email: batu.bora.tech@gmail.com
Classifier: Development Status :: 4 - Beta
Classifier: Intended Audience :: Developers
Classifier: Intended Audience :: System Administrators
Classifier: Programming Language :: Python :: 3
Classifier: Programming Language :: Python :: 3.6
Classifier: Programming Language :: Python :: 3.7
Classifier: Programming Language :: Python :: 3.8
Classifier: Programming Language :: Python :: 3.9
Classifier: Programming Language :: Python :: 3.10
Classifier: Operating System :: POSIX :: Linux
Classifier: Operating System :: MacOS :: MacOS X
Classifier: License :: OSI Approved :: MIT License
Classifier: Topic :: System :: Monitoring
Classifier: Topic :: System :: Networking
Requires-Python: >=3.6
License-File: LICENSE
Requires-Dist: jc>=1.12
